apputils/__init__.py
apputils-2.0.2.dist-info/LICENSE
apputils-2.0.2.dist-info/METADATA
apputils-2.0.2.dist-info/WHEEL
apputils-2.0.2.dist-info/top_level.txt
apputils-2.0.2.dist-info/zip-safe
apputils-2.0.2.dist-info/RECORD
