Metadata-Version: 2.1
Name: apputils
Version: 2.0.2
Summary: AppUtils Core package
Home-page: UNKNOWN
Author: hapylestat@apache.org
License: ASF
Platform: UNKNOWN
Classifier: Programming Language :: Python
Classifier: Programming Language :: Python :: 3
Classifier: Programming Language :: Python :: 3.8
Requires-Python: >=3.8
Provides-Extra: config
Requires-Dist: apputils-config ; extra == 'config'
Provides-Extra: curl
Requires-Dist: apputils-curl ; extra == 'curl'
Provides-Extra: discovery
Requires-Dist: apputils-discovery ; extra == 'discovery'
Provides-Extra: json2obj
Requires-Dist: apputils-json2obj ; extra == 'json2obj'
Provides-Extra: progressbar
Requires-Dist: apputils-progressbar ; extra == 'progressbar'
Provides-Extra: terminal
Requires-Dist: apputils-terminal ; extra == 'terminal'
